LICENSE
MANIFEST.in
README.rst
requirements.txt
setup.py
cmsplugin_tab_ui/__init__.py
cmsplugin_tab_ui/admin.py
cmsplugin_tab_ui/cms_plugins.py
cmsplugin_tab_ui/models.py
cmsplugin_tab_ui/tests.py
cmsplugin_tab_ui/views.py
cmsplugin_tab_ui.egg-info/PKG-INFO
cmsplugin_tab_ui.egg-info/SOURCES.txt
cmsplugin_tab_ui.egg-info/dependency_links.txt
cmsplugin_tab_ui.egg-info/not-zip-safe
cmsplugin_tab_ui.egg-info/requires.txt
cmsplugin_tab_ui.egg-info/top_level.txt
cmsplugin_tab_ui/locale/es/LC_MESSAGES/django.mo
cmsplugin_tab_ui/locale/es/LC_MESSAGES/django.po
cmsplugin_tab_ui/migrations/0001_initial.py
cmsplugin_tab_ui/migrations/__init__.py
cmsplugin_tab_ui/static/cmsplugin_tab_ui/css/tab.css
cmsplugin_tab_ui/templates/cmsplugin_tab_ui/tabfield.html
cmsplugin_tab_ui/templates/cmsplugin_tab_ui/tablist.html