Metadata-Version: 1.1
Name: cmsplugin-tab-ui
Version: 1.0
Summary: Tab plugin for django cms with Jquery ui
Home-page: http://github.com/luisza/cmsplugin-tab-ui
Author: Luisza
Author-email: luis.zarate@solvosoft.com
License: GPLv2
Keywords: tab django cms django-cms plugin
Platform: UNKNOWN
Classifier: Development Status :: 4 - Beta
Classifier: Environment :: Web Environment
Classifier: Intended Audience :: Developers
Classifier: License :: OSI Approved :: GNU General Public License v2 (GPLv2)
Classifier: Operating System :: OS Independent
Classifier: Programming Language :: Python
Classifier: Framework :: Django
